utilfab/__init__.py
utilfab/core.py
utilfab-1.3.0.dist-info/licenses/LICENSE
utilfab-1.3.0.dist-info/METADATA
utilfab-1.3.0.dist-info/WHEEL
utilfab-1.3.0.dist-info/top_level.txt
utilfab-1.3.0.dist-info/RECORD
