Metadata-Version: 2.4
Name: utilfab
Version: 1.3.0
Summary: Utilidades generales para procesamiento de texto, decisiones y formato
Author: Bautista Fabris, V4FAB
Author-email: V4FAB <managementv4fab@gmail.com>
License: MIT
Project-URL: Homepage, https://pypi.org/project/utilfab/
Project-URL: Source, https://github.com/V4FAB/utilfab
Classifier: Programming Language :: Python :: 3
Classifier: License :: OSI Approved :: MIT License
Classifier: Operating System :: OS Independent
Requires-Python: >=3.6
License-File: LICENSE
Dynamic: author
Dynamic: license-file
Dynamic: requires-python
